fix6/__init__.py
fix6/client.py
fix6/core/__init__.py
fix6/core/api_error.py
fix6/core/datetime_utils.py
fix6/core/jsonable_encoder.py
fix6/core/remove_none_from_headers.py
fix6/errors/__init__.py
fix6/errors/conflict_error.py
fix6/errors/not_found_error.py
fix6/errors/unprocessable_entity_error.py
fix6/py.typed
fix6/resources/__init__.py
fix6/resources/admin/__init__.py
fix6/resources/admin/client.py
fix6/resources/atmospheric/__init__.py
fix6/resources/atmospheric/client.py
fix6/resources/ghg/__init__.py
fix6/resources/ghg/client.py
fix6/resources/healthcheck/__init__.py
fix6/resources/healthcheck/client.py
fix6/resources/masks/__init__.py
fix6/resources/masks/client.py
fix6/resources/projects/__init__.py
fix6/resources/projects/client.py
fix6/resources/satellite/__init__.py
fix6/resources/satellite/client.py
fix6/resources/soil/__init__.py
fix6/resources/soil/client.py
fix6/resources/weather/__init__.py
fix6/resources/weather/client.py
fix6/types/__init__.py
fix6/types/climate_data.py
fix6/types/climate_returner.py
fix6/types/http_error.py
fix6/types/http_validation_error.py
fix6/types/index_metadata.py
fix6/types/project_area.py
fix6/types/project_supabase.py
fix6/types/validation_error.py
fix6/types/validation_error_loc_item.py
fix6/types/weather_data.py
fix6/types/weather_returner.py
fern_fix6-0.0.6.dist-info/METADATA
fern_fix6-0.0.6.dist-info/WHEEL
fern_fix6-0.0.6.dist-info/RECORD
